azkaban_client/__init__.py
azkaban_client/azkaban.py
azkaban_client/exceptions.py
azkaban_client/utils.py
azkaban_client-0.0.7.dist-info/DESCRIPTION.rst
azkaban_client-0.0.7.dist-info/METADATA
azkaban_client-0.0.7.dist-info/RECORD
azkaban_client-0.0.7.dist-info/WHEEL
azkaban_client-0.0.7.dist-info/metadata.json
azkaban_client-0.0.7.dist-info/top_level.txt
