Metadata-Version: 2.0
Name: azkaban-client
Version: 0.0.7
Summary: azkaban_client based on azkaban restful apis
Home-page: http://github.com/ruoyuchen/azkaban_client
Author: ruoyuchen
Author-email: smhsma@aliyun.com
License: MIT
Keywords: azkaban client
Platform: UNKNOWN
Classifier: Development Status :: 3 - Alpha
Classifier: License :: OSI Approved :: MIT License
Classifier: Programming Language :: Python :: 2.7
Classifier: Topic :: Text Processing :: Linguistic
Requires-Dist: requests
